pytest_level.py
pytest_level-0.1.3.dist-info/LICENSE
pytest_level-0.1.3.dist-info/METADATA
pytest_level-0.1.3.dist-info/WHEEL
pytest_level-0.1.3.dist-info/entry_points.txt
pytest_level-0.1.3.dist-info/top_level.txt
pytest_level-0.1.3.dist-info/RECORD
