Metadata-Version: 2.1
Name: pytest-level
Version: 0.1.3
Summary: Select tests of a given level or lower
Home-page: https://github.com/encukou/pytest-level
Author: Petr Viktorin
Author-email: encukou@gmail.com
License: MIT
Platform: UNKNOWN
Classifier: Framework :: Pytest
Classifier: License :: OSI Approved :: MIT License
Classifier: Programming Language :: Python :: 3
Classifier: Programming Language :: Python :: 3.6
Classifier: Programming Language :: Python :: 3.7
Requires-Dist: pytest
